CLA.md
CODE_OF_CONDUCT.md
CONTRIBUTING.md
MANIFEST.in
README.md
RELEASE_NOTES.md
requirements-test.txt
requirements.txt
setup.cfg
setup.py
meta1api/__init__.py
meta1api/exceptions.py
meta1api/meta1noderpc.py
meta1api/websocket.py
meta1base/__init__.py
meta1base/account.py
meta1base/asset_permissions.py
meta1base/bip38.py
meta1base/chains.py
meta1base/memo.py
meta1base/objects.py
meta1base/objecttypes.py
meta1base/operationids.py
meta1base/operations.py
meta1base/signedtransactions.py
meta1base/transactions.py
meta1t/__init__.py
meta1t/account.py
meta1t/amount.py
meta1t/asset.py
meta1t/block.py
meta1t/blockchain.py
meta1t/blockchainobject.py
meta1t/committee.py
meta1t/dex.py
meta1t/exceptions.py
meta1t/genesisbalance.py
meta1t/htlc.py
meta1t/instance.py
meta1t/market.py
meta1t/memo.py
meta1t/message.py
meta1t/meta1.py
meta1t/notify.py
meta1t/price.py
meta1t/proposal.py
meta1t/storage.py
meta1t/transactionbuilder.py
meta1t/utils.py
meta1t/vesting.py
meta1t/wallet.py
meta1t/witness.py
meta1t/worker.py
meta1t.egg-info/PKG-INFO
meta1t.egg-info/SOURCES.txt
meta1t.egg-info/dependency_links.txt
meta1t.egg-info/requires.txt
meta1t.egg-info/top_level.txt